pyvectorsearch/__init__.py
pyvectorsearch-0.0.1.dist-info/LICENSE
pyvectorsearch-0.0.1.dist-info/METADATA
pyvectorsearch-0.0.1.dist-info/WHEEL
pyvectorsearch-0.0.1.dist-info/RECORD
