Metadata-Version: 2.1
Name: pyvectorsearch
Version: 0.0.1
Summary: 
License: Apache-2.0
Author: sitmo
Author-email: thijs@sitmo.com
Requires-Python: >=3.8,<4.0
Classifier: License :: OSI Approved :: Apache Software License
Classifier: Programming Language :: Python :: 3
Classifier: Programming Language :: Python :: 3.8
Classifier: Programming Language :: Python :: 3.9
Classifier: Programming Language :: Python :: 3.10
Classifier: Programming Language :: Python :: 3.11
Requires-Dist: numpy (>=1.0)
